stochasticparrot/__init__.py
stochasticparrot-0.2.dist-info/METADATA
stochasticparrot-0.2.dist-info/WHEEL
stochasticparrot-0.2.dist-info/top_level.txt
stochasticparrot-0.2.dist-info/RECORD
