Metadata-Version: 2.1
Name: stochasticparrot
Version: 0.2
Summary: A package for handling errors with custom logging that lets OpenAI API make suggestions.
Home-page: https://github.com/yourusername/custom_error_handler
Author: Wes Ladd
Author-email: wesladd@traingrc.com
Classifier: Programming Language :: Python :: 3
Classifier: License :: OSI Approved :: MIT License
Classifier: Operating System :: OS Independent
Requires-Dist: openai
Requires-Dist: termcolor
Requires-Dist: sys
Requires-Dist: traceback
Requires-Dist: logging
Requires-Dist: getpass
